network_flow/__init__.py
network_flow/main.py
network_flow/main_test.py
network_flow_jajetloh_test-0.0.1.dist-info/METADATA
network_flow_jajetloh_test-0.0.1.dist-info/WHEEL
network_flow_jajetloh_test-0.0.1.dist-info/licenses/LICENSE.txt
network_flow_jajetloh_test-0.0.1.dist-info/RECORD
