Metadata-Version: 2.1
Name: network_flow_jajetloh_test
Version: 0.0.1
Summary: A small example package
Project-URL: Homepage, https://github.com/jajetloh/network_flow
Project-URL: Bug Tracker, https://github.com/jajetloh/network_flow/issues
Author-email: Ja-Jet Loh <jajet.codes@gmail.com>
License-File: LICENSE.txt
Classifier: License :: OSI Approved :: MIT License
Classifier: Operating System :: OS Independent
Classifier: Programming Language :: Python :: 3
Requires-Python: >=3.7
